pycprint.py
pycprint-1.1.0.dist-info/METADATA
pycprint-1.1.0.dist-info/WHEEL
pycprint-1.1.0.dist-info/top_level.txt
pycprint-1.1.0.dist-info/RECORD
