Metadata-Version: 2.1
Name: pycprint
Version: 1.1.0
Summary: Enhanced print function with timestamping, styling, and color options.
Home-page: https://github.com/CoataocCreate/printc-python
Author: Coataoc
Author-email: coataoccreater@gmail.com
License: MIT
Classifier: Programming Language :: Python :: 3
Classifier: License :: OSI Approved :: MIT License
Classifier: Operating System :: OS Independent
